{"id":262865,"name":"異世界かるてっと","name_cn":"异世界四重奏","type":2,"images":{"common":"https://lain.bgm.tv/r/400/pic/cover/l/c0/e9/262865_P6q49.jpg"},"rating":{"score":6.7},"summary":"「オーバーロード」「この素晴らしい世界に祝福を！」「Re:ゼロから始める異世界生活」「幼女戦記」。\r\n総シリーズ累計1600万部超え、BD＆DVDシリーズ総売上枚数50万枚超えを誇る4作品が、\r\nぷちキャラアニメになって大暴れ！\r\nある日突如として現れた謎のボタン。ポチっと押すと、なんとさらなる異世界へ転移してしまう！！\r\nそこには他世界から転移したキャラクターたちも大集合していて…！？\r\n「ぷれぷれぷれあです」「Re:プチから始める異世界生活」「ようじょしぇんき」と、\r\nぷちキャラアニメ界を牽引してきたスタッフ陣が、異世界系ライトノベル4作品のクロスオーバーアニメーションに挑む！","collection":{"wish":393,"doing":276,"collect":3590},"eps":12,"total_episodes":12}